textblur_summary/__init__.py
textblur_summary/main.py
textblur_summary/prompts.py
textblur_summary-2025.12.21130742.dist-info/METADATA
textblur_summary-2025.12.21130742.dist-info/WHEEL
textblur_summary-2025.12.21130742.dist-info/top_level.txt
textblur_summary-2025.12.21130742.dist-info/RECORD
