Metadata-Version: 2.4
Name: textblur-summary
Version: 2025.12.21130742
Summary: A new package that takes a text description of an image and returns a structured summary of the blurring tool's features and use cases. It processes user-provided text input about the tool, such as it
Author-email: textblur-summary <hi@eugene.plus>
License: MIT
Project-URL: Homepage, https://github.com/chigwell/textblur-summary
Requires-Python: >=3.9
Requires-Dist: langchain-llm7>=0.0.0
Requires-Dist: llmatch-messages>=0.0.0
Requires-Dist: langchain-core>=0.3.0
